Workbook

Sheet Instructions
A1: AMAZON ADVERTISING PROFITABILITY MODEL - USER GUIDE HOW TO USE THIS MODEL: 1. INPUT YOUR PARAMETERS (Profitability Model Sheet) - Edit the gray cells in column B with your brand's actual data - All calculations will auto-update based on your inputs - Leave unit columns alone; they are for reference 2. READ YOUR OUTPUTS (Blue section below inputs) - All metrics calculate automatically - No need to edit these cells; they contain formulas - Green highlights = healthy metrics - Yellow highlights = caution - Red highlights = problem 3. EXPLORE SCENARIOS (Scenario Analysis Sheet) - Compare your base case against 4 pre-built scenarios - Shows impact of price changes, cost inflation, organic growth, ad scaling - Helps you think through "what if" questions KEY METRICS EXPLAINED: GROSS MARGIN = SP - COGS Profit per unit before fees and advertising NET MARGIN (Ad Units) = Gross Margin - Amazon Fee - Ad Cost per Unit Profit per unit AFTER advertising (must be positive) ACOS = (Ad Spend / Ad Revenue) x 100 Percentage of ad revenue spent on ads. Lower is better. Aim for <30% TACOS = (Ad Spend / Total Revenue) x 100 Percentage of TOTAL revenue spent on ads. Better than ACOS for long-term health DECISION RULES: Green Light (Profitable, Efficient): - Profit > INR 500,000/month - ACOS < 30% - TACOS < 15% - Organic units > Ad units Action: Scale cautiously Yellow Light (Profitable but Risky): - Profit > 0 but < INR 500,000 - ACOS 30-40% - TACOS 15-20% Action: Optimize, don't scale Red Light (Not Profitable): - Profit < 0 - ACOS > 40% - TACOS > 25% Action: Stop or restructure COMMON SCENARIOS TO TEST: 1. Price Sensitivity: Change SP to +18% (e.g., INR 950) 2. Cost Pressure: Change COGS to +20% 3. Organic Growth: Increase Organic Units to 3,500 4. Ad Scaling: Double Ad Spend to INR 600,000 5. Competition: Decrease SP to INR 700 TIPS: 1. COGS should include manufacturing, packaging, fulfillment to Amazon 2. Fixed Costs should include team, warehousing, software, QA 3. Amazon Referral Fee varies: Electronics 8%, Beauty/Apparel 15%, Sports 12% 4. Update monthly with actual numbers 5. Review quarterly and adjust assumptions This model answers questions like: - Is this campaign profitable? - What is my break-even ad spend? - If I double ad spend, do I double profit? - What happens if costs increase 20%? - Should I raise or lower my price? - Is organic growth keeping up with paid?

Sheet Profitability Model
A1: AMAZON ADVERTISING PROFITABILITY MODEL
A2: GlowNest Premium Face Serum | Dynamic Scenario Analysis
A4: INPUT PARAMETERS (Edit These Cells)
A5: Parameter | B5: Value | C5: Unit | D5: Notes
A6: Selling Price (SP) | B6: 800 | C6: ₹ per unit | D6: List price on Amazon
A7: Cost of Goods Sold (COGS) | B7: 280 | C7: ₹ per unit | D7: Manufacturing + packaging + delivery
A8: Amazon Referral Fee (%) | B8: 0.12 | C8: % of SP | D8: Typical for skincare: 8-15%
A9: Monthly Ad Spend | B9: 300000 | C9: ₹ | D9: Total advertising budget
A10: Units Sold via Ads | B10: 1500 | C10: units/month | D10: Ad-attributed sales
A11: Organic Units Sold | B11: 2000 | C11: units/month | D11: Non-ad-attributed sales
A12: Fixed Costs (monthly) | B12: 150000 | C12: ₹ | D12: Warehousing, team, software
A14: CALCULATED OUTPUTS (Read-Only)
A15: Metric | B15: Value | C15: Unit | D15: Formula
A16: Gross Margin per Unit | B16: =B6-B7 -> 520 | C16: ₹ | D16: SP - COGS
A17: Amazon Fee per Unit | B17: =B6*B8 -> 96 | C17: ₹ | D17: SP × Fee%
A18: Ad Cost per Unit | B18: =B9/B10 -> 200 | C18: ₹ | D18: Ad Spend ÷ Ad Units
A19: Net Margin (Ad Units) | B19: =B14-B15-B16 -> #VALUE! | C19: ₹ | D19: Gross Margin - Amazon Fee - Ad Cost
A20: Net Margin (Organic Units) | B20: =B14-B15 -> #VALUE! | C20: ₹ | D20: Gross Margin - Amazon Fee
A21: Total Ad Revenue | B21: =B6*B10 -> 1200000 | C21: ₹ | D21: SP × Ad Units
A22: Total Organic Revenue | B22: =B6*B11 -> 1600000 | C22: ₹ | D22: SP × Organic Units
A23: Total Monthly Revenue | B23: =B20+B21 -> #VALUE! | C23: ₹ | D23: Ad Revenue + Organic Revenue
A24: Total Units Sold | B24: =B10+B11 -> 3500 | C24: units | D24: Ad Units + Organic Units
A25: Total Profit Contribution | B25: =(B17*B10)+(B18*B11) -> 544000 | C25: ₹ | D25: (Net Margin Ad × Ad Units) + (Net Margin Org × Org Units)
A26: Monthly Profit (after fixed) | B26: =B24-B12 -> -146500 | C26: ₹ | D26: Profit Contribution - Fixed Costs
A27: Profitability Margin % | B27: =(B25/B22)*100 -> 34 | C27: % | D27: (Monthly Profit ÷ Total Revenue) × 100
A28: ACOS (Advertising Cost of Sale) | B28: =(B9/B20)*100 -> #VALUE! | C28: % | D28: (Ad Spend ÷ Ad Revenue) × 100
A29: TACOS (Total Advertising Cost of Sale) | B29: =(B9/B22)*100 -> 18.75 | C29: % | D29: (Ad Spend ÷ Total Revenue) × 100
A30: Break-Even Ad Spend | B30: =(B18*B10) -> 300000 | C30: ₹ | D30: Net Margin Organic × Ad Units
A31: Payback Period | B31: =IF(B25>0,ROUND(B25/B9*30,1),"N/A") -> 54.4 | C31: days | D31: (Monthly Profit ÷ Ad Spend) × 30
A34: HEALTH CHECK
A35: Profit Status | B35: =IF(B25>0,"Profitable","Loss") -> Profitable | C35: B25 should be positive
A36: ACOS Status | B36: =IF(B28<0.3,"Excellent",IF(B28<0.35,"Good","Needs Work")) -> #VALUE! | C36: Aim for <30%
A37: TACOS Status | B37: =IF(B29<0.15,"Healthy","Monitor") -> Monitor | C37: Aim for <15%
A38: Net Margin (Ad) Status | B38: =IF(B17>0,"Positive","Negative") -> Positive | C38: Should be positive
A39: Organic Growth Signal | B39: =IF(B11>B10,"Strong","Weak") -> Strong | C39: Organic should grow

Sheet Scenario Analysis
A1: SCENARIO ANALYSIS
A2: Compare different business scenarios using the base model
A4: Base Case | B4: Price Increase | C4: Cost Inflation | D4: Organic Growth | E4: Ad Scaling
A5: Current parameters | B5: SP to 950 | C5: COGS +20% | D5: Organic to 3,500 | E5: Ad spend to 6L, units to 2,500
A7: Selling Price | B7: ='Profitability Model'!B6 -> 800 | C7: 950 | D7: ='Profitability Model'!B6 -> 800 | E7: ='Profitability Model'!B6 -> 800 | F7: ='Profitability Model'!B6 -> 800
A8: COGS | B8: ='Profitability Model'!B7 -> 280 | C8: ='Profitability Model'!B7 -> 280 | D8: ='Profitability Model'!B7*1.2 -> 336 | E8: ='Profitability Model'!B7 -> 280 | F8: ='Profitability Model'!B7 -> 280
A9: Ad Spend | B9: ='Profitability Model'!B9 -> 300000 | C9: ='Profitability Model'!B9 -> 300000 | D9: ='Profitability Model'!B9 -> 300000 | E9: ='Profitability Model'!B9 -> 300000 | F9: 600000
A10: Units (Ad) | B10: ='Profitability Model'!B10 -> 1500 | C10: ='Profitability Model'!B10 -> 1500 | D10: ='Profitability Model'!B10 -> 1500 | E10: ='Profitability Model'!B10 -> 1500 | F10: 2500
A11: Units (Organic) | B11: ='Profitability Model'!B11 -> 2000 | C11: ='Profitability Model'!B11 -> 2000 | D11: ='Profitability Model'!B11 -> 2000 | E11: 3500 | F11: ='Profitability Model'!B11 -> 2000
A12: Gross Margin | B12: ='Profitability Model'!B14 -> 0 | C12: =950-'Profitability Model'!B7 -> 670 | E12: ='Profitability Model'!B14 -> 0 | F12: ='Profitability Model'!B14 -> 0
A13: Net Margin (Ad) | B13: ='Profitability Model'!B17 -> 96 | C13: =(950-'Profitability Model'!B7)-(950*'Profitability Model'!B8)-('Profitability Model'!B9/'Profitability Model'!B10) -> 356 | E13: ='Profitability Model'!B17 -> 96 | F13: =('Profitability Model'!B14)-('Profitability Model'!B6*'Profitability Model'!B8)-(600000/2500) -> -336
A14: ACOS % | B14: ='Profitability Model'!B28 -> #VALUE! | C14: =('Profitability Model'!B9/(950*'Profitability Model'!B10))*100 -> 21.052632 | D14: =('Profitability Model'!B9/('Profitability Model'!B6*'Profitability Model'!B10))*100 -> 25 | E14: ='Profitability Model'!B28 -> #VALUE! | F14: =(600000/('Profitability Model'!B6*2500))*100 -> 30
A15: TACOS % | B15: ='Profitability Model'!B29 -> 18.75 | C15: =('Profitability Model'!B9/((950*'Profitability Model'!B10)+(950*'Profitability Model'!B11)))*100 -> 9.0225564 | D15: =('Profitability Model'!B9/(('Profitability Model'!B6*'Profitability Model'!B10)+('Profitability Model'!B6*'Profitability Model'!B11)))*100 -> 10.714286 | E15: =('Profitability Model'!B9/(('Profitability Model'!B6*'Profitability Model'!B10)+('Profitability Model'!B6*3500)))*100 -> 7.5 | F15: =(600000/(('Profitability Model'!B6*2500)+('Profitability Model'!B6*'Profitability Model'!B11)))*100 -> 16.666667
A16: Monthly Profit | B16: ='Profitability Model'!B25 -> 544000 | C16: =((950-'Profitability Model'!B7)-(950*'Profitability Model'!B8)-('Profitability Model'!B9/'Profitability Model'!B10))*'Profitability Model'!B10+((950-'Profitability Model'!B7)-(950*'Profitability Model'!B8))*'Profitability Model'!B11-'Profitability Model'!B12 -> 1496000 | E16: =('Profitability Model'!B17*'Profitability Model'!B10)+('Profitability Model'!B18*3500)-'Profitability Model'!B12 -> 694000 | F16: =(('Profitability Model'!B14-('Profitability Model'!B6*'Profitability Model'!B8)-(600000/2500))*2500)+(('Profitability Model'!B14-('Profitability Model'!B6*'Profitability Model'!B8))*'Profitability Model'!B11)-'Profitability Model'!B12 -> -1182000
A17: Profit Margin % | B17: ='Profitability Model'!B26 -> -146500 | C17: =(((950-'Profitability Model'!B7)-(950*'Profitability Model'!B8)-('Profitability Model'!B9/'Profitability Model'!B10))*'Profitability Model'!B10+((950-'Profitability Model'!B7)-(950*'Profitability Model'!B8))*'Profitability Model'!B11-'Profitability Model'!B12)/((950*'Profitability Model'!B10)+(950*'Profitability Model'!B11))*100 -> 44.992481 | E17: =(('Profitability Model'!B17*'Profitability Model'!B10)+('Profitability Model'!B18*3500)-'Profitability Model'!B12)/(('Profitability Model'!B6*'Profitability Model'!B10)+('Profitability Model'!B6*3500))*100 -> 17.35 | F17: =((('Profitability Model'!B14-('Profitability Model'!B6*'Profitability Model'!B8)-(600000/2500))*2500)+(('Profitability Model'!B14-('Profitability Model'!B6*'Profitability Model'!B8))*'Profitability Model'!B11)-'Profitability Model'!B12)/(('Profitability Model'!B6*2500)+('Profitability Model'!B6*'Profitability Model'!B11))*100 -> -32.833333
